{
  "__inputs": [
    {
      "name": "DS_OPEN-FALCON",
      "label": "open-falcon",
      "description": "",
      "type": "datasource",
      "pluginId": "fastweb-openfalcon-datasource",
      "pluginName": "Open-Falcon"
    }
  ],
  "__requires": [
    {
      "type": "datasource",
      "id": "fastweb-openfalcon-datasource",
      "name": "Open-Falcon",
      "version": "1.0.0"
    },
    {
      "type": "grafana",
      "id": "grafana",
      "name": "Grafana",
      "version": "4.3.2"
    },
    {
      "type": "panel",
      "id": "graph",
      "name": "Graph",
      "version": ""
    }
  ],
  "annotations": {
    "list": []
  },
  "editable": true,
  "gnetId": null,
  "graphTooltip": 0,
  "hideControls": false,
  "id": null,
  "links": [],
  "rows": [
    {
      "collapse": false,
      "height": 377,
      "panels": [
        {
          "aliasColors": {},
          "bars": false,
          "dashLength": 10,
          "dashes": false,
          "datasource": "${DS_OPEN-FALCON}",
          "fill": 1,
          "id": 20,
          "legend": {
            "alignAsTable": true,
            "avg": true,
            "current": true,
            "max": true,
            "min": true,
            "show": true,
            "sort": "current",
            "sortDesc": true,
            "total": false,
            "values": true
          },
          "lines": true,
          "linewidth": 1,
          "links": [],
          "nullPointMode": "connected",
          "percentage": false,
          "pointradius": 5,
          "points": false,
          "renderer": "flot",
          "seriesOverrides": [],
          "spaceLength": 10,
          "span": 6,
          "stack": false,
          "steppedLine": false,
          "targets": [
            {
              "dsType": "influxdb",
              "groupBy": [
                {
                  "params": [
                    "$__interval"
                  ],
                  "type": "time"
                },
                {
                  "params": [
                    "null"
                  ],
                  "type": "fill"
                }
              ],
              "orderByTime": "ASC",
              "policy": "default",
              "refId": "A",
              "resultFormat": "time_series",
              "select": [
                [
                  {
                    "params": [
                      "value"
                    ],
                    "type": "field"
                  },
                  {
                    "params": [],
                    "type": "mean"
                  }
                ]
              ],
              "tags": [],
              "target": "$host#rabbitmq#messages_ready/name=[[q]]",
              "textEditor": true
            }
          ],
          "thresholds": [],
          "timeFrom": null,
          "timeShift": null,
          "title": "队列中处于等待被消费状态消息数",
          "tooltip": {
            "shared": true,
            "sort": 0,
            "value_type": "individual"
          },
          "type": "graph",
          "xaxis": {
            "buckets": null,
            "mode": "time",
            "name": null,
            "show": true,
            "values": []
          },
          "yaxes": [
            {
              "format": "short",
              "label": null,
              "logBase": 1,
              "max": null,
              "min": null,
              "show": true
            },
            {
              "format": "short",
              "label": null,
              "logBase": 1,
              "max": null,
              "min": null,
              "show": true
            }
          ]
        },
        {
          "aliasColors": {},
          "bars": false,
          "dashLength": 10,
          "dashes": false,
          "datasource": "${DS_OPEN-FALCON}",
          "fill": 1,
          "id": 21,
          "legend": {
            "alignAsTable": true,
            "avg": true,
            "current": true,
            "max": true,
            "min": true,
            "show": true,
            "sort": "current",
            "sortDesc": true,
            "total": false,
            "values": true
          },
          "lines": true,
          "linewidth": 1,
          "links": [],
          "nullPointMode": "connected",
          "percentage": false,
          "pointradius": 5,
          "points": false,
          "renderer": "flot",
          "seriesOverrides": [],
          "spaceLength": 10,
          "span": 6,
          "stack": false,
          "steppedLine": false,
          "targets": [
            {
              "dsType": "influxdb",
              "groupBy": [
                {
                  "params": [
                    "$__interval"
                  ],
                  "type": "time"
                },
                {
                  "params": [
                    "null"
                  ],
                  "type": "fill"
                }
              ],
              "orderByTime": "ASC",
              "policy": "default",
              "refId": "A",
              "resultFormat": "time_series",
              "select": [
                [
                  {
                    "params": [
                      "value"
                    ],
                    "type": "field"
                  },
                  {
                    "params": [],
                    "type": "mean"
                  }
                ]
              ],
              "tags": [],
              "target": "$host#rabbitmq#messages_unacknowledged/name=[[q]]",
              "textEditor": true
            }
          ],
          "thresholds": [],
          "timeFrom": null,
          "timeShift": null,
          "title": "队列中处于消费中状态的消息数",
          "tooltip": {
            "shared": true,
            "sort": 0,
            "value_type": "individual"
          },
          "type": "graph",
          "xaxis": {
            "buckets": null,
            "mode": "time",
            "name": null,
            "show": true,
            "values": []
          },
          "yaxes": [
            {
              "format": "short",
              "label": null,
              "logBase": 1,
              "max": null,
              "min": null,
              "show": true
            },
            {
              "format": "short",
              "label": null,
              "logBase": 1,
              "max": null,
              "min": null,
              "show": true
            }
          ]
        }
      ],
      "repeat": null,
      "repeatIteration": null,
      "repeatRowId": null,
      "showTitle": false,
      "title": "Dashboard Row",
      "titleSize": "h6"
    },
    {
      "collapse": false,
      "height": 340,
      "panels": [
        {
          "aliasColors": {},
          "bars": false,
          "dashLength": 10,
          "dashes": false,
          "datasource": "${DS_OPEN-FALCON}",
          "fill": 1,
          "id": 3,
          "legend": {
            "alignAsTable": true,
            "avg": true,
            "current": true,
            "max": true,
            "min": true,
            "show": true,
            "sort": "current",
            "sortDesc": true,
            "total": false,
            "values": true
          },
          "lines": true,
          "linewidth": 1,
          "links": [],
          "nullPointMode": "connected",
          "percentage": false,
          "pointradius": 5,
          "points": false,
          "renderer": "flot",
          "seriesOverrides": [],
          "spaceLength": 10,
          "span": 6,
          "stack": false,
          "steppedLine": false,
          "targets": [
            {
              "dsType": "influxdb",
              "groupBy": [
                {
                  "params": [
                    "$__interval"
                  ],
                  "type": "time"
                },
                {
                  "params": [
                    "null"
                  ],
                  "type": "fill"
                }
              ],
              "orderByTime": "ASC",
              "policy": "default",
              "refId": "A",
              "resultFormat": "time_series",
              "select": [
                [
                  {
                    "params": [
                      "value"
                    ],
                    "type": "field"
                  },
                  {
                    "params": [],
                    "type": "mean"
                  }
                ]
              ],
              "tags": [],
              "target": "$host#rabbitmq#deliver_rate/name=[[q]]",
              "textEditor": true
            }
          ],
          "thresholds": [],
          "timeFrom": null,
          "timeShift": null,
          "title": "deliver的速率",
          "tooltip": {
            "shared": true,
            "sort": 0,
            "value_type": "individual"
          },
          "type": "graph",
          "xaxis": {
            "buckets": null,
            "mode": "time",
            "name": null,
            "show": true,
            "values": []
          },
          "yaxes": [
            {
              "format": "short",
              "label": null,
              "logBase": 1,
              "max": null,
              "min": null,
              "show": true
            },
            {
              "format": "short",
              "label": null,
              "logBase": 1,
              "max": null,
              "min": null,
              "show": true
            }
          ]
        },
        {
          "aliasColors": {},
          "bars": false,
          "dashLength": 10,
          "dashes": false,
          "datasource": "${DS_OPEN-FALCON}",
          "fill": 1,
          "id": 5,
          "legend": {
            "alignAsTable": true,
            "avg": true,
            "current": true,
            "max": true,
            "min": true,
            "show": true,
            "sort": "current",
            "sortDesc": true,
            "total": false,
            "values": true
          },
          "lines": true,
          "linewidth": 1,
          "links": [],
          "nullPointMode": "connected",
          "percentage": false,
          "pointradius": 5,
          "points": false,
          "renderer": "flot",
          "seriesOverrides": [],
          "spaceLength": 10,
          "span": 6,
          "stack": false,
          "steppedLine": false,
          "targets": [
            {
              "dsType": "influxdb",
              "groupBy": [
                {
                  "params": [
                    "$__interval"
                  ],
                  "type": "time"
                },
                {
                  "params": [
                    "null"
                  ],
                  "type": "fill"
                }
              ],
              "orderByTime": "ASC",
              "policy": "default",
              "refId": "A",
              "resultFormat": "time_series",
              "select": [
                [
                  {
                    "params": [
                      "value"
                    ],
                    "type": "field"
                  },
                  {
                    "params": [],
                    "type": "mean"
                  }
                ]
              ],
              "tags": [],
              "target": "$host#rabbitmq#deliver_get_rate/name=[[q]]",
              "textEditor": true
            }
          ],
          "thresholds": [],
          "timeFrom": null,
          "timeShift": null,
          "title": "deliver_get的速率",
          "tooltip": {
            "shared": true,
            "sort": 0,
            "value_type": "individual"
          },
          "type": "graph",
          "xaxis": {
            "buckets": null,
            "mode": "time",
            "name": null,
            "show": true,
            "values": []
          },
          "yaxes": [
            {
              "format": "short",
              "label": null,
              "logBase": 1,
              "max": null,
              "min": null,
              "show": true
            },
            {
              "format": "short",
              "label": null,
              "logBase": 1,
              "max": null,
              "min": null,
              "show": true
            }
          ]
        }
      ],
      "repeat": null,
      "repeatIteration": null,
      "repeatRowId": null,
      "showTitle": false,
      "title": "Dashboard Row",
      "titleSize": "h6"
    },
    {
      "collapse": false,
      "height": 305,
      "panels": [
        {
          "aliasColors": {},
          "bars": false,
          "dashLength": 10,
          "dashes": false,
          "datasource": "${DS_OPEN-FALCON}",
          "fill": 1,
          "id": 6,
          "legend": {
            "alignAsTable": true,
            "avg": true,
            "current": true,
            "max": true,
            "min": true,
            "show": true,
            "sort": "current",
            "sortDesc": true,
            "total": false,
            "values": true
          },
          "lines": true,
          "linewidth": 1,
          "links": [],
          "nullPointMode": "connected",
          "percentage": false,
          "pointradius": 5,
          "points": false,
          "renderer": "flot",
          "seriesOverrides": [],
          "spaceLength": 10,
          "span": 6,
          "stack": false,
          "steppedLine": false,
          "targets": [
            {
              "dsType": "influxdb",
              "groupBy": [
                {
                  "params": [
                    "$__interval"
                  ],
                  "type": "time"
                },
                {
                  "params": [
                    "null"
                  ],
                  "type": "fill"
                }
              ],
              "orderByTime": "ASC",
              "policy": "default",
              "refId": "A",
              "resultFormat": "time_series",
              "select": [
                [
                  {
                    "params": [
                      "value"
                    ],
                    "type": "field"
                  },
                  {
                    "params": [],
                    "type": "mean"
                  }
                ]
              ],
              "tags": [],
              "target": "$host#rabbitmq#publish_rate/name=[[q]]",
              "textEditor": true
            }
          ],
          "thresholds": [],
          "timeFrom": null,
          "timeShift": null,
          "title": "publish的速率",
          "tooltip": {
            "shared": true,
            "sort": 0,
            "value_type": "individual"
          },
          "type": "graph",
          "xaxis": {
            "buckets": null,
            "mode": "time",
            "name": null,
            "show": true,
            "values": []
          },
          "yaxes": [
            {
              "format": "short",
              "label": null,
              "logBase": 1,
              "max": null,
              "min": null,
              "show": true
            },
            {
              "format": "short",
              "label": null,
              "logBase": 1,
              "max": null,
              "min": null,
              "show": true
            }
          ]
        },
        {
          "aliasColors": {},
          "bars": false,
          "dashLength": 10,
          "dashes": false,
          "datasource": "${DS_OPEN-FALCON}",
          "fill": 1,
          "id": 7,
          "legend": {
            "alignAsTable": true,
            "avg": true,
            "current": true,
            "max": true,
            "min": true,
            "show": true,
            "sort": "current",
            "sortDesc": true,
            "total": false,
            "values": true
          },
          "lines": true,
          "linewidth": 1,
          "links": [],
          "nullPointMode": "connected",
          "percentage": false,
          "pointradius": 5,
          "points": false,
          "renderer": "flot",
          "seriesOverrides": [],
          "spaceLength": 10,
          "span": 6,
          "stack": false,
          "steppedLine": false,
          "targets": [
            {
              "dsType": "influxdb",
              "groupBy": [
                {
                  "params": [
                    "$__interval"
                  ],
                  "type": "time"
                },
                {
                  "params": [
                    "null"
                  ],
                  "type": "fill"
                }
              ],
              "orderByTime": "ASC",
              "policy": "default",
              "refId": "A",
              "resultFormat": "time_series",
              "select": [
                [
                  {
                    "params": [
                      "value"
                    ],
                    "type": "field"
                  },
                  {
                    "params": [],
                    "type": "mean"
                  }
                ]
              ],
              "tags": [],
              "target": "$host#rabbitmq#ack_rate/name=[[q]]",
              "textEditor": true
            }
          ],
          "thresholds": [],
          "timeFrom": null,
          "timeShift": null,
          "title": "消费者ack的速率",
          "tooltip": {
            "shared": true,
            "sort": 0,
            "value_type": "individual"
          },
          "type": "graph",
          "xaxis": {
            "buckets": null,
            "mode": "time",
            "name": null,
            "show": true,
            "values": []
          },
          "yaxes": [
            {
              "format": "short",
              "label": null,
              "logBase": 1,
              "max": null,
              "min": null,
              "show": true
            },
            {
              "format": "short",
              "label": null,
              "logBase": 1,
              "max": null,
              "min": null,
              "show": true
            }
          ]
        }
      ],
      "repeat": null,
      "repeatIteration": null,
      "repeatRowId": null,
      "showTitle": false,
      "title": "Dashboard Row",
      "titleSize": "h6"
    },
    {
      "collapse": false,
      "height": 283,
      "panels": [
        {
          "aliasColors": {},
          "bars": false,
          "dashLength": 10,
          "dashes": false,
          "datasource": "${DS_OPEN-FALCON}",
          "fill": 1,
          "id": 22,
          "legend": {
            "alignAsTable": true,
            "avg": true,
            "current": true,
            "max": true,
            "min": true,
            "show": true,
            "sort": "current",
            "sortDesc": true,
            "total": false,
            "values": true
          },
          "lines": true,
          "linewidth": 1,
          "links": [],
          "nullPointMode": "connected",
          "percentage": false,
          "pointradius": 5,
          "points": false,
          "renderer": "flot",
          "seriesOverrides": [],
          "spaceLength": 10,
          "span": 8,
          "stack": false,
          "steppedLine": false,
          "targets": [
            {
              "dsType": "influxdb",
              "groupBy": [
                {
                  "params": [
                    "$__interval"
                  ],
                  "type": "time"
                },
                {
                  "params": [
                    "null"
                  ],
                  "type": "fill"
                }
              ],
              "orderByTime": "ASC",
              "policy": "default",
              "refId": "A",
              "resultFormat": "time_series",
              "select": [
                [
                  {
                    "params": [
                      "value"
                    ],
                    "type": "field"
                  },
                  {
                    "params": [],
                    "type": "mean"
                  }
                ]
              ],
              "tags": [],
              "target": "$host#rabbitmq#messages_total/name=[[q]]",
              "textEditor": true
            }
          ],
          "thresholds": [],
          "timeFrom": null,
          "timeShift": null,
          "title": "队列中所有未完成消费的消息数",
          "tooltip": {
            "shared": true,
            "sort": 0,
            "value_type": "individual"
          },
          "type": "graph",
          "xaxis": {
            "buckets": null,
            "mode": "time",
            "name": null,
            "show": true,
            "values": []
          },
          "yaxes": [
            {
              "format": "short",
              "label": null,
              "logBase": 1,
              "max": null,
              "min": null,
              "show": true
            },
            {
              "format": "short",
              "label": null,
              "logBase": 1,
              "max": null,
              "min": null,
              "show": true
            }
          ]
        }
      ],
      "repeat": null,
      "repeatIteration": null,
      "repeatRowId": null,
      "showTitle": false,
      "title": "Dashboard Row",
      "titleSize": "h6"
    }
  ],
  "schemaVersion": 14,
  "style": "dark",
  "tags": [
    "RabbitMQ"
  ],
  "templating": {
    "list": [
      {
        "allValue": null,
        "current": {},
        "datasource": "${DS_OPEN-FALCON}",
        "hide": 0,
        "includeAll": true,
        "label": "host",
        "multi": true,
        "name": "host",
        "options": [],
        "query": ".+",
        "refresh": 1,
        "regex": "/(.+mq)/",
        "sort": 0,
        "tagValuesQuery": "",
        "tags": [],
        "tagsQuery": "",
        "type": "query",
        "useTags": false
      },
      {
        "allValue": null,
        "current": {},
        "datasource": "${DS_OPEN-FALCON}",
        "hide": 0,
        "includeAll": true,
        "label": "q",
        "multi": true,
        "name": "q",
        "options": [],
        "query": "$host#rabbitmq#ack_rate/name=",
        "refresh": 1,
        "regex": "/(.+)/",
        "sort": 0,
        "tagValuesQuery": "",
        "tags": [],
        "tagsQuery": "",
        "type": "query",
        "useTags": false
      }
    ]
  },
  "time": {
    "from": "now-1h",
    "to": "now"
  },
  "timepicker": {
    "refresh_intervals": [
      "5s",
      "10s",
      "30s",
      "1m",
      "5m",
      "15m",
      "30m",
      "1h",
      "2h",
      "1d"
    ],
    "time_options": [
      "5m",
      "15m",
      "1h",
      "6h",
      "12h",
      "24h",
      "2d",
      "7d",
      "30d"
    ]
  },
  "timezone": "browser",
  "title": "RabbitMQ",
  "version": 15
}